<annotation>
	<folder>train</folder>
	<filename>289_jpg.rf.b21771b0ad65bc8b90eef88159174185.jpg</filename>
	<path>C:\Users\saura\Desktop\Preparation\images\train\289_jpg.rf.b21771b0ad65bc8b90eef88159174185.jpg</path>
	<source>
		<database>Unknown</database>
	</source>
	<size>
		<width>800</width>
		<height>800</height>
		<depth>3</depth>
	</size>
	<segmented>0</segmented>
	<object>
		<name>Katakam</name>
		<pose>Unspecified</pose>
		<truncated>0</truncated>
		<difficult>0</difficult>
		<bndbox>
			<xmin>312</xmin>
			<ymin>59</ymin>
			<xmax>688</xmax>
			<ymax>666</ymax>
		</bndbox>
	</object>
</annotation>
