<annotation>
	<folder>train</folder>
	<filename>318_jpg.rf.2104a494678628f0ee81ce16639575ca.jpg</filename>
	<path>C:\Users\saura\Desktop\Preparation\images\train\318_jpg.rf.2104a494678628f0ee81ce16639575ca.jpg</path>
	<source>
		<database>Unknown</database>
	</source>
	<size>
		<width>800</width>
		<height>800</height>
		<depth>3</depth>
	</size>
	<segmented>0</segmented>
	<object>
		<name>Mushti</name>
		<pose>Unspecified</pose>
		<truncated>0</truncated>
		<difficult>0</difficult>
		<bndbox>
			<xmin>238</xmin>
			<ymin>128</ymin>
			<xmax>593</xmax>
			<ymax>485</ymax>
		</bndbox>
	</object>
</annotation>
